yt_music/__init__.py
yt_music/__main__.py
yt_music/__version__.py
yt_music/__yt_music__.py
yt_music-0.0.8.dist-info/LICENSE
yt_music-0.0.8.dist-info/METADATA
yt_music-0.0.8.dist-info/WHEEL
yt_music-0.0.8.dist-info/entry_points.txt
yt_music-0.0.8.dist-info/RECORD
