Metadata-Version: 2.1
Name: yt-music
Version: 0.0.8
Summary: A command line YouTube Music client.
License: GPLv3
Author: DemonKingSwarn
Author-email: rockingswarn@gmail.com
Requires-Python: >=3.10,<4.0
Classifier: License :: Other/Proprietary License
Classifier: Programming Language :: Python :: 3
Classifier: Programming Language :: Python :: 3.10
Classifier: Programming Language :: Python :: 3.11
Classifier: Programming Language :: Python :: 3.12
Requires-Dist: bs4 (>=0.0.2,<0.0.3)
Requires-Dist: httpx (==0.23.0)
Requires-Dist: krfzf-py (>=0.0.4,<0.0.5)
Requires-Dist: pypresence (==4.3.0)
Requires-Dist: yt-dlp (>=2023.12.30,<2024.0.0)
